LiOH_Cpp.cp39-win_amd64.pyd
LiOH/__init__.py
LiOH/add.py
LiOH/division.py
LiOH/multiply.py
LiOH/subtract.py
LiOH/version.py
LiOH/adv/__init__.py
LiOH/adv/sqrt.py
LiOH/cpp/__init__.py
LiOH/cpp/cpp_fun.py
LiOH/file/__init__.py
LiOH/file/json.py
LiOH/file/path_dir.py
LiOH/file/read_write_remove_copy.py
LiOH-0.1.14.dist-info/METADATA
LiOH-0.1.14.dist-info/WHEEL
LiOH-0.1.14.dist-info/top_level.txt
LiOH-0.1.14.dist-info/RECORD
