Metadata-Version: 2.1
Name: LiOH
Version: 0.1.14
Summary: A LiOH package
Home-page: http://www.LiOH.xyz/
Author: LiOH
Author-email: 908716811@qq.com
License: UNKNOWN
Platform: UNKNOWN
Requires-Dist: numpy
